<metadata><figure alt="http://images.metmuseum.org/CRDImages/ao/web-large/DP315033.jpg"><imagedata src="http://www.mappingoceaniadenison.org/temp_images/temp_images/68b66d022c4176e0f5e4f2ad862c7834_img_0.jpg"></imagedata><link alt="http://images.metmuseum.org/CRDImages/ao/web-large/DP315033.jpg"/><figure alt="http://images.metmuseum.org/CRDImages/ao/web-large/DP145510.jpg"><imagedata src="http://www.mappingoceaniadenison.org/temp_images/temp_images/68b66d022c4176e0f5e4f2ad862c7834_img_1.jpg"></imagedata><link alt="http://images.metmuseum.org/CRDImages/ao/web-large/DP145510.jpg"/><obj_type>Mask <obj_type>Mask <indig_name>Kavat <indig_name>Mai <cult_loc>Baining People (New Britain) <cult_loc>Iatmul People (New Guinea) <date>1972 or 1973 <date>Late 19th- Early 20th Century <materials>Bamboo, barkcloth, paints <materials>Wood, paint, fish vertebrae <dimensions>H. 39 x W. 33 x D. 22 in. <dimensions>H. 28 x W. 3 7/8 x D. 4 3/16 in. <inst_access>The Metropolitan Museum of Art 2004.552.1  <inst_access>The Metropolitan Museum of Art, 1979.206.1480</metadata>